ableton_mcp/__init__.py
ableton_mcp/connection.py
ableton_mcp/server.py
ableton_mcp/tools/__init__.py
ableton_mcp/tools/application.py
ableton_mcp/tools/browser.py
ableton_mcp/tools/clip.py
ableton_mcp/tools/clip_slot.py
ableton_mcp/tools/device.py
ableton_mcp/tools/executor.py
ableton_mcp/tools/export.py
ableton_mcp/tools/midimap.py
ableton_mcp/tools/scene.py
ableton_mcp/tools/song.py
ableton_mcp/tools/track.py
ableton_mcp/tools/view.py
ableton_mcp_server-0.1.0.dist-info/LICENSE
ableton_mcp_server-0.1.0.dist-info/METADATA
ableton_mcp_server-0.1.0.dist-info/WHEEL
ableton_mcp_server-0.1.0.dist-info/entry_points.txt
ableton_mcp_server-0.1.0.dist-info/RECORD
