Metadata-Version: 2.3
Name: ableton-mcp-server
Version: 0.1.0
Summary: MCP server for controlling Ableton Live via Claude Code
License: MIT
Keywords: ableton,mcp,ai,music,claude,osc
Author: ldraney
Requires-Python: >=3.11,<4.0
Classifier: Development Status :: 4 - Beta
Classifier: Intended Audience :: Developers
Classifier: License :: OSI Approved :: MIT License
Classifier: Operating System :: OS Independent
Classifier: Programming Language :: Python :: 3
Classifier: Programming Language :: Python :: 3.11
Classifier: Programming Language :: Python :: 3.12
Classifier: Programming Language :: Python :: 3.13
Classifier: Topic :: Multimedia :: Sound/Audio
Requires-Dist: abletonosc-client (>=1.1.0,<2.0.0)
Requires-Dist: fastmcp (>=2.3.4)
Requires-Dist: mido (>=1.3.3,<2.0.0)
Requires-Dist: song-executor (>=0.1.0,<0.2.0)
Requires-Dist: song-schema (>=0.1.0,<0.2.0)
Project-URL: Homepage, https://github.com/ldraney/ableton-mcp
Project-URL: Repository, https://github.com/ldraney/ableton-mcp
